modern_benchmark/__init__.py
modern_benchmark/requirements.txt
modern_benchmark/core/__init__.py
modern_benchmark/core/api.py
modern_benchmark/core/collector.py
modern_benchmark/core/context.py
modern_benchmark/core/decorator.py
modern_benchmark/core/globals.py
modern_benchmark/struct/__init__.py
modern_benchmark/struct/benchmarkresult.py
modern_benchmark/struct/benchmarkstats.py
modern_benchmark/util/__init__.py
modern_benchmark/util/jsonreader.py
modern_benchmark/util/jsonutils.py
modern_benchmark/util/logging.py
modern_benchmark/util/printcolor.py
modern_benchmark-0.1.0.dist-info/METADATA
modern_benchmark-0.1.0.dist-info/WHEEL
modern_benchmark-0.1.0.dist-info/licenses/LICENSE
modern_benchmark-0.1.0.dist-info/RECORD
