Metadata-Version: 2.4
Name: modern-benchmark
Version: 0.1.0
Summary: A Python package for benchmarking functions on modern versions of Python.
Project-URL: Homepage, https://github.com/connor33341/modern-benchmark
Project-URL: Repository, https://github.com/connor33341/modern-benchmark
Author-email: connor33341 <connor@connor33341.dev>
License: MIT License
License-File: LICENSE
Classifier: License :: OSI Approved :: MIT License
Classifier: Programming Language :: Python :: 3
Classifier: Programming Language :: Python :: 3.8
Classifier: Programming Language :: Python :: 3.9
Classifier: Programming Language :: Python :: 3.10
Classifier: Programming Language :: Python :: 3.11
Requires-Python: >=3.9
Requires-Dist: colorama
Requires-Dist: psutil
